asciilove-0.0.1.dist-info/RECORD
asciilove-0.0.1.dist-info/DESCRIPTION.rst
asciilove-0.0.1.dist-info/entry_points.txt
asciilove-0.0.1.dist-info/METADATA
asciilove-0.0.1.dist-info/WHEEL
asciilove-0.0.1.dist-info/metadata.json
asciilove-0.0.1.dist-info/top_level.txt
asciilove/commandline.py
asciilove/converter.py
asciilove/__init__.py
