Metadata-Version: 2.0
Name: asciilove
Version: 0.0.1
Summary: Convert images to ASCII art in your command line
Home-page: https://github.com/hamvocke/asciilove
Author: Hermann Vocke
Author-email: ham@hamvocke.com
License: MIT
Keywords: ascii art asciiart
Platform: UNKNOWN
Classifier: Development Status :: 3 - Alpha
Classifier: Environment :: Console
Classifier: Intended Audience :: End Users/Desktop
Classifier: Topic :: Software Development :: Build Tools
Classifier: License :: OSI Approved :: MIT License
Classifier: Programming Language :: Python :: 3
Classifier: Programming Language :: Python :: 3.3
Classifier: Programming Language :: Python :: 3.4
Classifier: Programming Language :: Python :: 3.5
Classifier: Topic :: Artistic Software
Requires-Dist: wand
